python_stretch/__init__.py
python_stretch/Signalsmith.cp311-win_amd64.pyd
python_stretch-0.2.0.dist-info/METADATA
python_stretch-0.2.0.dist-info/WHEEL
python_stretch-0.2.0.dist-info/licenses/LICENSE
python_stretch-0.2.0.dist-info/RECORD
