Metadata-Version: 2.1
Name: python-stretch
Version: 0.2.0
Summary: A Python Wrapprer of the Signalsmith Stretch C++ library for pitch and time stretching
Author-Email: Gregorio Andrea Giudici <greg.giudici96@gmail.com>
Classifier: License :: OSI Approved :: MIT License
Classifier: Programming Language :: C++
Classifier: Programming Language :: Python
Classifier: Topic :: Multimedia :: Sound/Audio
Project-URL: Homepage, https://github.com/gregogiudici/python-stretch
Requires-Python: >=3.9
